LICENSE
MANIFEST.in
README.rst
setup.cfg
setup.py
django_testhook.egg-info/PKG-INFO
django_testhook.egg-info/SOURCES.txt
django_testhook.egg-info/dependency_links.txt
django_testhook.egg-info/not-zip-safe
django_testhook.egg-info/requires.txt
django_testhook.egg-info/top_level.txt
testhook/__init__.py
testhook/tests.py
testhook/templatetags/__init__.py
testhook/templatetags/testhook.py